{
  "crl": {
    "config": {
      "d_z": 24,
      "d_model": 64,
      "n_heads": 4,
      "n_layers": 2,
      "training_mode": "contrastive",
      "prior_type": "standard",
      "frontend_type": "multiscale",
      "fused_seq_len": 32,
      "morlet_kernel_size": 257,
      "multiscale_pool_stride": 16,
      "morlet_pool_stride": 64,
      "morlet_use_phase": false,
      "morlet_learnable_w0": false,
      "morlet_learnable_lr_mult": 0.1,
      "stage2_encoder_lr_mult": 0.3,
      "morlet_per_sensor_params": {
        "audio": {
          "freq_min": 20.0,
          "freq_max": 8000.0,
          "out_channels_frac": 1.0,
          "w0": 6.0,
          "target_tokens": 32,
          "receptive_cycles": 3.0
        },
        "seismic": {
          "freq_min": 2.0,
          "freq_max": 40.0,
          "out_channels_frac": 1.0,
          "w0": 6.0,
          "target_tokens": 32,
          "receptive_cycles": 3.0
        }
      },
      "batch_size": 64,
      "lr": 0.0003,
      "lr_min": 0.0001,
      "wd": 0.0001,
      "n_epochs": 100,
      "num_workers": 4,
      "early_stop_patience": 25,
      "lambda_interv": 1.0,
      "lambda_aux_pres": 1.0,
      "lambda_aux_type": 1.0,
      "lambda_aux_prox": 0.1,
      "beta_step": 0.02,
      "kl_floor": 0.01,
      "kl_target": 0.5,
      "recon_min_delta": 0.0001,
      "horizon_stride_sec": 0.7,
      "n_partners_same_type": 1,
      "n_partners_diff_type": 1,
      "n_partners_cross_ds": 1,
      "contrastive_temperature": 0.1,
      "contrastive_d_proj": 64
    },
    "sensors": [
      "audio",
      "seismic"
    ],
    "crl_elapsed_min": 36.63,
    "trajectory": {
      "best_contrastive_loss": 5.082277,
      "best_epoch": 9,
      "checkpoints": {
        "crl_best.pth": "selected by val_contrastive_loss (lower = better)",
        "crl_final.pth": "last epoch (may be post-early-stop)"
      },
      "best_ref_elbo": Infinity,
      "best_ref_elbo_epoch": -1,
      "best_aux_type_f1": 0.0,
      "best_aux_type_epoch": 0,
      "total_epochs": 35
    },
    "crl_dir": "saved_crl/oneshot/2026-04-24_16-17-43/crl"
  },
  "probes": [
    {
      "run_name": "linear_ztype__crl_best",
      "probe_mode": "linear_ztype",
      "ckpt_name": "crl_best.pth",
      "save_dir": "saved_crl/oneshot/2026-04-24_16-17-43/downstream/linear_ztype__crl_best",
      "val_pres_f1": 0.4161,
      "val_pres_acc": 0.3989,
      "val_type_f1": 0.392,
      "val_type_acc": 0.4549,
      "val_loss": 1.5991,
      "best_epoch": 1
    },
    {
      "run_name": "mlp_ztype__crl_best",
      "probe_mode": "mlp_ztype",
      "ckpt_name": "crl_best.pth",
      "save_dir": "saved_crl/oneshot/2026-04-24_16-17-43/downstream/mlp_ztype__crl_best",
      "val_pres_f1": 0.7382,
      "val_pres_acc": 0.6393,
      "val_type_f1": 0.4483,
      "val_type_acc": 0.5069,
      "val_loss": 1.5063,
      "best_epoch": 43
    },
    {
      "run_name": "linear_fullz__crl_best",
      "probe_mode": "linear_fullz",
      "ckpt_name": "crl_best.pth",
      "save_dir": "saved_crl/oneshot/2026-04-24_16-17-43/downstream/linear_fullz__crl_best",
      "val_pres_f1": 0.5848,
      "val_pres_acc": 0.508,
      "val_type_f1": 0.4647,
      "val_type_acc": 0.5252,
      "val_loss": 1.4617,
      "best_epoch": 2
    }
  ],
  "evals": [
    {
      "run_name": "linear_fullz__crl_best",
      "probe_mode": "linear_fullz",
      "ckpt_name": "crl_best.pth",
      "split": "full",
      "include_datasets": null,
      "n_windows": 21436,
      "presence": {
        "accuracy": 0.4922,
        "precision": 0.8151,
        "recall": 0.3989,
        "specificity": 0.75,
        "f1": 0.5356,
        "balanced_accuracy": 0.5745,
        "mcc": 0.1371,
        "tp": 6278,
        "fp": 1424,
        "fn": 9461,
        "tn": 4273
      },
      "type": {
        "accuracy": 0.435,
        "macro_f1": 0.4033,
        "macro_f1_support_only": 0.4033,
        "macro_precision": 0.4181,
        "macro_recall": 0.4205,
        "per_class": {
          "pedestrian": {
            "precision": 0.0979,
            "recall": 0.117,
            "f1": 0.1066,
            "support": 3051
          },
          "light": {
            "precision": 0.3528,
            "recall": 0.589,
            "f1": 0.4413,
            "support": 2416
          },
          "medium": {
            "precision": 0.7919,
            "recall": 0.5023,
            "f1": 0.6147,
            "support": 6976
          },
          "heavy": {
            "precision": 0.4297,
            "recall": 0.4739,
            "f1": 0.4507,
            "support": 3296
          }
        },
        "confusion_matrix": [
          [
            357,
            1284,
            58,
            1352
          ],
          [
            280,
            1423,
            155,
            558
          ],
          [
            2966,
            343,
            3504,
            163
          ],
          [
            43,
            983,
            708,
            1562
          ]
        ]
      }
    },
    {
      "run_name": "linear_fullz__crl_best",
      "probe_mode": "linear_fullz",
      "ckpt_name": "crl_best.pth",
      "split": "focal",
      "include_datasets": [
        "focal"
      ],
      "n_windows": 14534,
      "presence": {
        "accuracy": 0.46,
        "precision": 0.9126,
        "recall": 0.2719,
        "specificity": 0.9343,
        "f1": 0.419,
        "balanced_accuracy": 0.6031,
        "mcc": 0.227,
        "tp": 2830,
        "fp": 271,
        "fn": 7577,
        "tn": 3856
      },
      "type": {
        "accuracy": 0.2211,
        "macro_f1": 0.2168,
        "macro_f1_support_only": 0.2168,
        "macro_precision": 0.2208,
        "macro_recall": 0.2697,
        "per_class": {
          "pedestrian": {
            "precision": 0.0989,
            "recall": 0.117,
            "f1": 0.1072,
            "support": 3051
          },
          "light": {
            "precision": 0.3081,
            "recall": 0.5486,
            "f1": 0.3946,
            "support": 2080
          },
          "medium": {
            "precision": 0.2074,
            "recall": 0.0276,
            "f1": 0.0487,
            "support": 3440
          },
          "heavy": {
            "precision": 0.2686,
            "recall": 0.3856,
            "f1": 0.3166,
            "support": 1836
          }
        },
        "confusion_matrix": [
          [
            357,
            1284,
            58,
            1352
          ],
          [
            244,
            1141,
            155,
            540
          ],
          [
            2966,
            343,
            95,
            36
          ],
          [
            43,
            935,
            150,
            708
          ]
        ]
      }
    },
    {
      "run_name": "linear_fullz__crl_best",
      "probe_mode": "linear_fullz",
      "ckpt_name": "crl_best.pth",
      "split": "iobt",
      "include_datasets": [
        "iobt"
      ],
      "n_windows": 936,
      "presence": {
        "accuracy": 0.5427,
        "precision": 0.7015,
        "recall": 0.5411,
        "specificity": 0.546,
        "f1": 0.6109,
        "balanced_accuracy": 0.5435,
        "mcc": 0.0823,
        "tp": 336,
        "fp": 143,
        "fn": 285,
        "tn": 172
      },
      "type": {
        "accuracy": 0.7118,
        "macro_f1": 0.3845,
        "macro_f1_support_only": 0.769,
        "macro_precision": 0.4384,
        "macro_recall": 0.3502,
        "per_class": {
          "pedestrian": {
            "precision": 0.0,
            "recall": 0.0,
            "f1": 0.0,
            "support": 0
          },
          "light": {
            "precision": 0.8545,
            "recall": 0.8393,
            "f1": 0.8468,
            "support": 336
          },
          "medium": {
            "precision": 0.0,
            "recall": 0.0,
            "f1": 0.0,
            "support": 0
          },
          "heavy": {
            "precision": 0.8989,
            "recall": 0.5614,
            "f1": 0.6911,
            "support": 285
          }
        },
        "confusion_matrix": [
          [
            0,
            0,
            0,
            0
          ],
          [
            36,
            282,
            0,
            18
          ],
          [
            0,
            0,
            0,
            0
          ],
          [
            0,
            48,
            77,
            160
          ]
        ]
      }
    },
    {
      "run_name": "linear_ztype__crl_best",
      "probe_mode": "linear_ztype",
      "ckpt_name": "crl_best.pth",
      "split": "full",
      "include_datasets": null,
      "n_windows": 21436,
      "presence": {
        "accuracy": 0.3887,
        "precision": 0.7815,
        "recall": 0.2325,
        "specificity": 0.8204,
        "f1": 0.3584,
        "balanced_accuracy": 0.5265,
        "mcc": 0.0566,
        "tp": 3659,
        "fp": 1023,
        "fn": 12080,
        "tn": 4674
      },
      "type": {
        "accuracy": 0.3277,
        "macro_f1": 0.3076,
        "macro_f1_support_only": 0.3076,
        "macro_precision": 0.3248,
        "macro_recall": 0.3137,
        "per_class": {
          "pedestrian": {
            "precision": 0.0509,
            "recall": 0.0659,
            "f1": 0.0574,
            "support": 3051
          },
          "light": {
            "precision": 0.3301,
            "recall": 0.4243,
            "f1": 0.3713,
            "support": 2416
          },
          "medium": {
            "precision": 0.6388,
            "recall": 0.3833,
            "f1": 0.4791,
            "support": 6976
          },
          "heavy": {
            "precision": 0.2795,
            "recall": 0.3814,
            "f1": 0.3226,
            "support": 3296
          }
        },
        "confusion_matrix": [
          [
            201,
            942,
            310,
            1598
          ],
          [
            498,
            1025,
            175,
            718
          ],
          [
            3129,
            249,
            2674,
            924
          ],
          [
            123,
            889,
            1027,
            1257
          ]
        ]
      }
    },
    {
      "run_name": "linear_ztype__crl_best",
      "probe_mode": "linear_ztype",
      "ckpt_name": "crl_best.pth",
      "split": "focal",
      "include_datasets": [
        "focal"
      ],
      "n_windows": 14534,
      "presence": {
        "accuracy": 0.3668,
        "precision": 0.909,
        "recall": 0.1286,
        "specificity": 0.9675,
        "f1": 0.2253,
        "balanced_accuracy": 0.548,
        "mcc": 0.1436,
        "tp": 1338,
        "fp": 134,
        "fn": 9069,
        "tn": 3993
      },
      "type": {
        "accuracy": 0.1658,
        "macro_f1": 0.1708,
        "macro_f1_support_only": 0.1708,
        "macro_precision": 0.1499,
        "macro_recall": 0.2088,
        "per_class": {
          "pedestrian": {
            "precision": 0.0517,
            "recall": 0.0659,
            "f1": 0.0579,
            "support": 3051
          },
          "light": {
            "precision": 0.2949,
            "recall": 0.4178,
            "f1": 0.3457,
            "support": 2080
          },
          "medium": {
            "precision": 0.0332,
            "recall": 0.0067,
            "f1": 0.0111,
            "support": 3440
          },
          "heavy": {
            "precision": 0.2199,
            "recall": 0.3448,
            "f1": 0.2685,
            "support": 1836
          }
        },
        "confusion_matrix": [
          [
            201,
            942,
            310,
            1598
          ],
          [
            450,
            869,
            165,
            596
          ],
          [
            3118,
            247,
            23,
            52
          ],
          [
            120,
            889,
            194,
            633
          ]
        ]
      }
    },
    {
      "run_name": "linear_ztype__crl_best",
      "probe_mode": "linear_ztype",
      "ckpt_name": "crl_best.pth",
      "split": "iobt",
      "include_datasets": [
        "iobt"
      ],
      "n_windows": 936,
      "presence": {
        "accuracy": 0.4754,
        "precision": 0.6958,
        "recall": 0.372,
        "specificity": 0.6794,
        "f1": 0.4848,
        "balanced_accuracy": 0.5257,
        "mcc": 0.0507,
        "tp": 231,
        "fp": 101,
        "fn": 390,
        "tn": 214
      },
      "type": {
        "accuracy": 0.4138,
        "macro_f1": 0.2579,
        "macro_f1_support_only": 0.5159,
        "macro_precision": 0.3632,
        "macro_recall": 0.2047,
        "per_class": {
          "pedestrian": {
            "precision": 0.0,
            "recall": 0.0,
            "f1": 0.0,
            "support": 0
          },
          "light": {
            "precision": 1.0,
            "recall": 0.4643,
            "f1": 0.6341,
            "support": 336
          },
          "medium": {
            "precision": 0.0,
            "recall": 0.0,
            "f1": 0.0,
            "support": 0
          },
          "heavy": {
            "precision": 0.4529,
            "recall": 0.3544,
            "f1": 0.3976,
            "support": 285
          }
        },
        "confusion_matrix": [
          [
            0,
            0,
            0,
            0
          ],
          [
            48,
            156,
            10,
            122
          ],
          [
            0,
            0,
            0,
            0
          ],
          [
            3,
            0,
            181,
            101
          ]
        ]
      }
    },
    {
      "run_name": "mlp_ztype__crl_best",
      "probe_mode": "mlp_ztype",
      "ckpt_name": "crl_best.pth",
      "split": "full",
      "include_datasets": null,
      "n_windows": 21436,
      "presence": {
        "accuracy": 0.5928,
        "precision": 0.8247,
        "recall": 0.5657,
        "specificity": 0.6679,
        "f1": 0.6711,
        "balanced_accuracy": 0.6168,
        "mcc": 0.2064,
        "tp": 8903,
        "fp": 1892,
        "fn": 6836,
        "tn": 3805
      },
      "type": {
        "accuracy": 0.3519,
        "macro_f1": 0.3247,
        "macro_f1_support_only": 0.3247,
        "macro_precision": 0.3413,
        "macro_recall": 0.3175,
        "per_class": {
          "pedestrian": {
            "precision": 0.0784,
            "recall": 0.1082,
            "f1": 0.0909,
            "support": 3051
          },
          "light": {
            "precision": 0.3946,
            "recall": 0.2819,
            "f1": 0.3288,
            "support": 2416
          },
          "medium": {
            "precision": 0.5268,
            "recall": 0.4419,
            "f1": 0.4807,
            "support": 6976
          },
          "heavy": {
            "precision": 0.3656,
            "recall": 0.4381,
            "f1": 0.3986,
            "support": 3296
          }
        },
        "confusion_matrix": [
          [
            330,
            572,
            893,
            1256
          ],
          [
            526,
            681,
            673,
            536
          ],
          [
            3157,
            22,
            3083,
            714
          ],
          [
            198,
            451,
            1203,
            1444
          ]
        ]
      }
    },
    {
      "run_name": "mlp_ztype__crl_best",
      "probe_mode": "mlp_ztype",
      "ckpt_name": "crl_best.pth",
      "split": "focal",
      "include_datasets": [
        "focal"
      ],
      "n_windows": 14534,
      "presence": {
        "accuracy": 0.5428,
        "precision": 0.9082,
        "recall": 0.4021,
        "specificity": 0.8975,
        "f1": 0.5574,
        "balanced_accuracy": 0.6498,
        "mcc": 0.2904,
        "tp": 4185,
        "fp": 423,
        "fn": 6222,
        "tn": 3704
      },
      "type": {
        "accuracy": 0.1748,
        "macro_f1": 0.2039,
        "macro_f1_support_only": 0.2039,
        "macro_precision": 0.2061,
        "macro_recall": 0.2082,
        "per_class": {
          "pedestrian": {
            "precision": 0.0795,
            "recall": 0.1082,
            "f1": 0.0917,
            "support": 3051
          },
          "light": {
            "precision": 0.3928,
            "recall": 0.324,
            "f1": 0.3551,
            "support": 2080
          },
          "medium": {
            "precision": 0.0775,
            "recall": 0.0494,
            "f1": 0.0603,
            "support": 3440
          },
          "heavy": {
            "precision": 0.2748,
            "recall": 0.3513,
            "f1": 0.3084,
            "support": 1836
          }
        },
        "confusion_matrix": [
          [
            330,
            572,
            893,
            1256
          ],
          [
            483,
            674,
            586,
            337
          ],
          [
            3139,
            22,
            170,
            109
          ],
          [
            198,
            448,
            545,
            645
          ]
        ]
      }
    },
    {
      "run_name": "mlp_ztype__crl_best",
      "probe_mode": "mlp_ztype",
      "ckpt_name": "crl_best.pth",
      "split": "iobt",
      "include_datasets": [
        "iobt"
      ],
      "n_windows": 936,
      "presence": {
        "accuracy": 0.5769,
        "precision": 0.6578,
        "recall": 0.7552,
        "specificity": 0.2254,
        "f1": 0.7031,
        "balanced_accuracy": 0.4903,
        "mcc": -0.0215,
        "tp": 469,
        "fp": 244,
        "fn": 152,
        "tn": 71
      },
      "type": {
        "accuracy": 0.1836,
        "macro_f1": 0.1006,
        "macro_f1_support_only": 0.2013,
        "macro_precision": 0.2624,
        "macro_recall": 0.099,
        "per_class": {
          "pedestrian": {
            "precision": 0.0,
            "recall": 0.0,
            "f1": 0.0,
            "support": 0
          },
          "light": {
            "precision": 0.7,
            "recall": 0.0208,
            "f1": 0.0405,
            "support": 336
          },
          "medium": {
            "precision": 0.0,
            "recall": 0.0,
            "f1": 0.0,
            "support": 0
          },
          "heavy": {
            "precision": 0.3497,
            "recall": 0.3754,
            "f1": 0.3621,
            "support": 285
          }
        },
        "confusion_matrix": [
          [
            0,
            0,
            0,
            0
          ],
          [
            43,
            7,
            87,
            199
          ],
          [
            0,
            0,
            0,
            0
          ],
          [
            0,
            3,
            175,
            107
          ]
        ]
      }
    }
  ]
}